{
  "ngDeps": {
    "1": "",
    "3": [
      {
        "1": "package:angular2/core.dart",
        "5": false
      },
      {
        "1": "header/login-componenet.dart",
        "5": false
      },
      {
        "1": "system-control-room/sign-up/sign-up-componenet.dart",
        "5": false
      },
      {
        "1": "footer/footer-componenet.dart",
        "5": false
      }
    ],
    "5": [
      {
        "1": "AppComponent",
        "4": [
          {
            "1": "Component",
            "3": [
              {
                "1": "selector",
                "2": "'body'"
              },
              {
                "1": "directives",
                "2": "const [LoginComponent, SignUpComponent, FooterComponent]"
              },
              {
                "1": "styleUrls",
                "2": "const ['app.css']"
              },
              {
                "1": "templateUrl",
                "2": "'app-view.html'"
              }
            ],
            "4": false,
            "5": true,
            "6": true,
            "7": true,
            "8": false
          }
        ],
        "8": [
          {
            "2": "LoginComponent"
          },
          {
            "2": "SignUpComponent"
          },
          {
            "2": "FooterComponent"
          }
        ]
      }
    ],
    "6": "app-componenet.dart",
    "10": [
      {
        "1": "package:angular2/core.template.dart",
        "4": "i0"
      },
      {
        "1": "header/login-componenet.template.dart",
        "4": "i1"
      },
      {
        "1": "system-control-room/sign-up/sign-up-componenet.template.dart",
        "4": "i2"
      },
      {
        "1": "footer/footer-componenet.template.dart",
        "4": "i3"
      }
    ]
  },
  "AppComponent": {
    "kind": "type",
    "value": {
      "class": "Directive",
      "isComponent": true,
      "dynamicLoadable": true,
      "selector": "body",
      "exportAs": null,
      "type": {
        "class": "Type",
        "name": "AppComponent",
        "moduleUrl": "asset:SmartPeopleUI/lib/app-componenet.dart",
        "prefix": null,
        "isHost": false,
        "constConstructor": null,
        "diDeps": []
      },
      "changeDetection": 5,
      "inputs": {},
      "outputs": {},
      "hostListeners": {},
      "hostProperties": {},
      "hostAttributes": {},
      "lifecycleHooks": [],
      "template": {
        "encapsulation": 0,
        "template": "<header class=\"clearfix\"></header>\r\n<sign-up-control-room></sign-up-control-room>\r\n<footer></footer>",
        "templateUrl": "asset:SmartPeopleUI/lib/app-view.html",
        "styles": [],
        "styleUrls": [
          "asset:SmartPeopleUI/lib/app.css"
        ],
        "ngContentSelectors": []
      },
      "providers": []
    }
  },
  "definesAlias": false
}